dagtimers/__init__.py
dagtimers-0.1.2.dist-info/METADATA
dagtimers-0.1.2.dist-info/WHEEL
dagtimers-0.1.2.dist-info/top_level.txt
dagtimers-0.1.2.dist-info/RECORD
