Metadata-Version: 2.1
Name: dagtimers
Version: 0.1.2
Summary: Nicely displayed timers.
Home-page: https://github.com/automorphis/dagtimers
Author: Michael P. Lane
Author-email: mlanetheta@gmail.com
